django_admin_advanced_search/__init__.py
django_admin_advanced_search/mixins.py
django_admin_advanced_search/parser.py
django_admin_advanced_search-0.1.6.dist-info/licenses/LICENSE
django_admin_advanced_search-0.1.6.dist-info/METADATA
django_admin_advanced_search-0.1.6.dist-info/WHEEL
django_admin_advanced_search-0.1.6.dist-info/top_level.txt
django_admin_advanced_search-0.1.6.dist-info/RECORD
