Metadata-Version: 2.4
Name: django-admin-advanced-search
Version: 0.1.6
Summary: Advanced search syntax for Django Admin
Author-email: shifenhutu <shifenhutu@example.com>
License: MIT
Project-URL: Homepage, https://github.com/shifenhutu/django-admin-advanced-search
Project-URL: Repository, https://github.com/shifenhutu/django-admin-advanced-search
Project-URL: Documentation, https://github.com/shifenhutu/django-admin-advanced-search/blob/main/README.md
Project-URL: Issues, https://github.com/shifenhutu/django-admin-advanced-search/issues
Keywords: django,admin,search,filter,advanced-search
Classifier: Development Status :: 4 - Beta
Classifier: Environment :: Web Environment
Classifier: Framework :: Django
Classifier: Framework :: Django :: 5.1
Classifier: Framework :: Django :: 5.2
Classifier: Intended Audience :: Developers
Classifier: License :: OSI Approved :: MIT License
Classifier: Operating System :: OS Independent
Classifier: Programming Language :: Python
Classifier: Programming Language :: Python :: 3.12
Requires-Python: >=3.12
License-File: LICENSE
Requires-Dist: Django>=5.1
Dynamic: license-file
